django_memcache_admin-0.2.0.dist-info/LICENSE.txt
django_memcache_admin-0.2.0.dist-info/pydist.json
django_memcache_admin-0.2.0.dist-info/WHEEL
django_memcache_admin-0.2.0.dist-info/METADATA
django_memcache_admin-0.2.0.dist-info/DESCRIPTION.rst
django_memcache_admin-0.2.0.dist-info/RECORD
django_memcache_admin-0.2.0.dist-info/top_level.txt
memcache_admin/views.py
memcache_admin/tests.py
memcache_admin/admin.py
memcache_admin/models.py
memcache_admin/__init__.py
memcache_admin/management/__init__.py
memcache_admin/management/commands/__init__.py
memcache_admin/management/commands/flushmemcache.py
memcache_admin/templatetags/__init__.py
memcache_admin/templatetags/memcache_admin.py
memcache_admin/templates/memcache_admin/server_status.html
memcache_admin/templates/memcache_admin/dashboard.html
memcache_admin/templates/memcache_admin/dashboard_error.html
memcache_admin/templates/memcache_admin/stats.html
memcache_admin/templates/memcache_admin/slabs.html
