Metadata-Version: 2.0
Name: django-memcache-admin
Version: 0.2.0
Summary: Memcache admin for Django.
Home-page: https://github.com/ianare/django-memcache-admin
Author: Ianaré Sévi
Author-email: ianare@gmail.com
License: LGPLv3+
Keywords: memcached
Platform: UNKNOWN
Classifier: Development Status :: 4 - Beta
Classifier: Environment :: Web Environment
Classifier: Framework :: Django
Classifier: Intended Audience :: Developers
Classifier: Intended Audience :: System Administrators
Classifier: License :: OSI Approved :: GNU Lesser General Public License v3 or later (LGPLv3+)
Classifier: Operating System :: OS Independent
Classifier: Programming Language :: Python :: 2
Classifier: Programming Language :: Python :: 3
Classifier: Topic :: Internet :: WWW/HTTP :: Site Management
Requires-Dist: Django (>=1.6)
